toughastgen/__init__.py
toughastgen/build_ast.py
toughastgen-0.0.5.dist-info/LICENSE
toughastgen-0.0.5.dist-info/METADATA
toughastgen-0.0.5.dist-info/WHEEL
toughastgen-0.0.5.dist-info/top_level.txt
toughastgen-0.0.5.dist-info/RECORD
