Metadata-Version: 2.1
Name: toughastgen
Version: 0.0.5
Summary: A small example package
Home-page: https://github.com/DT6A/HSE_Python
Author: Denis Tarasov
Author-email: dt6cgsg@gmail.com
License: UNKNOWN
Platform: UNKNOWN
Classifier: Programming Language :: Python :: 3
Classifier: License :: OSI Approved :: MIT License
Classifier: Operating System :: OS Independent
Requires-Python: >=3.6
License-File: LICENSE
Requires-Dist: astunparse (==1.6.3)
Requires-Dist: networkx (==2.6.3)
Requires-Dist: matplotlib
Requires-Dist: pydot (>=1.2.4)
